LICENSE.txt
MANIFEST.in
README.txt
setup.py
django_workflows.egg-info/PKG-INFO
django_workflows.egg-info/SOURCES.txt
django_workflows.egg-info/dependency_links.txt
django_workflows.egg-info/namespace_packages.txt
django_workflows.egg-info/not-zip-safe
django_workflows.egg-info/requires.txt
django_workflows.egg-info/top_level.txt
workflows/__init__.py
workflows/admin.py
workflows/models.py
workflows/tests.py
workflows/urls.py
workflows/utils.py
workflows/views.py
workflows/locale/de/LC_MESSAGES/django.mo
workflows/locale/de/LC_MESSAGES/django.po