Metadata-Version: 1.1
Name: django-workflows
Version: 1.1
Summary: Generic workflow engine for Django.
Home-page: http://www.iqpp.de
Author: Kai Diefenbach
Author-email: kai.diefenbach@iqpp.de
License: BSD
Keywords: django workflows
Platform: UNKNOWN
Classifier: Development Status :: 4 - Beta
Classifier: Environment :: Web Environment
Classifier: Framework :: Django
Classifier: License :: OSI Approved :: BSD License
Classifier: Operating System :: OS Independent
Classifier: Programming Language :: Python
